norm_benchmark/__init__.py
norm_benchmark/backend/__init__.py
norm_benchmark/backend/app.py
norm_benchmark/backend/evaluator.py
norm_benchmark/backend/metrics.py
norm_benchmark/backend/prompts.py
norm_benchmark/backend/utils.py
norm_benchmark/constants.py
norm_benchmark/frontend/dashboard.py
norm_benchmark/norm_cli.py
norm_benchmark-0.14.1.dist-info/METADATA
norm_benchmark-0.14.1.dist-info/WHEEL
norm_benchmark-0.14.1.dist-info/entry_points.txt
norm_benchmark-0.14.1.dist-info/RECORD
