Metadata-Version: 2.1
Name: norm-benchmark
Version: 0.14.1
Summary: coNstructiOn pRoject Manager
Author: Bruno Chicelli
Author-email: b.rosilva1@gmail.com
Requires-Python: >=3.12,<4.0
Classifier: Programming Language :: Python :: 3
Classifier: Programming Language :: Python :: 3.12
Requires-Dist: boto3 (>=1.36.26,<2.0.0)
Requires-Dist: fire (>=0.7.0,<0.8.0)
Requires-Dist: scikit-learn (>=1.6.1,<2.0.0)
Requires-Dist: sentence-transformers (>=3.4.1,<4.0.0)
Requires-Dist: streamlit (>=1.42.2,<2.0.0)
Requires-Dist: transformers (>=4.49.0,<5.0.0)
